signalk_client/__init__.py
signalk_client/client.py
signalk_client/data.py
signalk_client/datum.py
signalk_client/vessel.py
signalk_client/zeroconf.py
signalk_client/include/meta.json
tests/__init__.py
tests/data.py
tests/datum.py
tests/vessel.py
signalk_client-0.2.3.dist-info/LICENSE
signalk_client-0.2.3.dist-info/METADATA
signalk_client-0.2.3.dist-info/WHEEL
signalk_client-0.2.3.dist-info/top_level.txt
signalk_client-0.2.3.dist-info/RECORD
