Metadata-Version: 2.1
Name: signalk-client
Version: 0.2.3
Summary: python client library for the SignalK protocol
Home-page: https://github.com/ph1l/python-signalk-client
Author: Philip J Freeman
Author-email: elektron@halo.nu
License: GPL3
Keywords: signalk
License-File: LICENSE
Requires-Dist: requests
Requires-Dist: websocket-client
Requires-Dist: enum-compat
Requires-Dist: netifaces
Requires-Dist: six
